[
    {
       "eventName": "Mount.release",
       "and_list": ["has successfully delivered a component", "MountController"],
       "or_list": [],
       "search_list": [],
       "keyName":"(Array\\d+)",
       "eventType": "transition"
    },

    {
      "eventName":"Interferometry.start",
       "and_list": ["Interferometry observing mode starting"],
       "or_list": [],
       "search_list": [],
       "keyName":"(Array\\d+)",
       "eventType": "transition"
    },
    {
      "eventName":"SingleDish.start",
       "and_list": ["Single dish observing mode starting up."],
       "or_list": [],
       "search_list": [],
       "keyName":"(Array\\d+)",
       "eventType": "transition"
    },
    {
      "eventName":"Holography.start",
       "and_list": ["Tower holography observing mode starting up"],
       "or_list": [],
       "search_list": [],
       "keyName":"(Array\\d+)",
       "eventType": "transition"
    },
    {
      "eventName":"VLBI.start",
       "and_list": ["VLBI observing mode starting."],
       "or_list": [],
       "search_list": [],
       "keyName":"(Array\\d+)",
       "eventType": "transition"
    },
    {
       "eventName":"Observation.stop",
       "and_list": [],
       "or_list": ["to archive ASDM", "Waiting for ASDM to be archived","Previous execution block hasn't been properly finished."],
       "search_list": [],
       "keyName":"(Array\\d+)",
       "eventType": "transition"
    },

    {
       "eventName": "Scan.start",
       "and_list": ["with scan intent"],
       "or_list": [],
       "search_list": [],
       "keyName":"(Array\\d+)",
       "eventType": "transition"
    },

    {
       "eventName": "SubScan.start",
       "and_list": ["sub-scan", "has an intent of"],
       "or_list": [],
       "search_list": [],
       "keyName":"(Array\\d+)",
       "eventType": "transition"
    },
    {
      "eventName": "AutomaticArray.destruction",
       "and_list": [],
       "or_list": [],
       "search_list": ["(Deactivating offshoots.)", "(ArrayStateBase)"],
       "keyName":"(Array\\d+)",
       "eventType": "final"
    },
    {
       "eventName": "AutomaticArray.initialize",
       "and_list": [],
       "or_list": [],
       "search_list": ["(initialize called)", "(AutomaticArrayImpl2)"],
       "keyName":"(Array\\d+)",
       "eventType": "initial"
    },
    {
       "eventName": "AutomaticArray.observe",
       "and_list": [],
       "or_list": [],
       "search_list": ["({alma.Control.Array.AutomaticArrayOperationalState::observe})"],
       "keyName":"(Array\\d+)",
       "eventType": "transition"
    }
]
